axon/ServiceNode.py
axon/__init__.py
axon/chunking.py
axon/client.py
axon/config.py
axon/inline_executor.py
axon/log_metrics.py
axon/pytest.ini
axon/serializers.py
axon/stubs.py
axon/transport_client.py
axon/transport_worker.py
axon/utils.py
axon/worker.py
axon/HTTP_transport/__init__.py
axon/HTTP_transport/client.py
axon/HTTP_transport/config.py
axon/HTTP_transport/worker.py
axon/reflector/__init__.py
axon/reflector/config.py
axon/reflector/host_script.py
axon/reflector/refl_app.py
axon/reflector/reflector_script.py
axon/reflector/worker.py
axon/reflector/worker_script.py
axon/reflector/tests/ITL_test.py
axon/reflector/tests/__init__.py
axon/tests/ServiceNode_test.py
axon/tests/__init__.py
axon/tests/client_test.py
axon/tests/conftest.py
axon/tests/service_client_test.py
axon/tests/transport_test.py
axon/tests/worker_test.py
axon_ECRG-0.2.4.dist-info/METADATA
axon_ECRG-0.2.4.dist-info/WHEEL
axon_ECRG-0.2.4.dist-info/top_level.txt
axon_ECRG-0.2.4.dist-info/RECORD
