Metadata-Version: 2.1
Name: axon-ECRG
Version: 0.2.4
Summary: RPC proxy framework
Home-page: https://github.com/DuncanMays/axon-ECRG
Requires-Dist: pytest
Requires-Dist: pytest-asyncio
Requires-Dist: flask
Requires-Dist: urllib3
Requires-Dist: requests
Requires-Dist: aiohttp
Requires-Dist: python-socketio[client]
Requires-Dist: psutil
Requires-Dist: cloudpickle
